{
  "layouts": [
    {
      "layoutName": "landscape",
      "children": [
        {
          "rotation": "0",
          "y": -90,
          "scaleX": "1",
          "scaleY": "1",
          "width": "546.70",
          "height": "202.65",
          "name": "back",
          "children": [
            {
              "texture": "shadow",
              "y": -10,
              "scaleX": "11.88",
              "scaleY": "4.40",
              "width": "546.70",
              "height": "202.65",
              "name": "instance25",
              "rotation": "0",
              "type": "uiElement",
              "x": -26
            },
            {
              "texture": "tile_bg_2",
              "y": 35,
              "scaleX": "1",
              "scaleY": "1",
              "width": "40",
              "height": "40",
              "name": "instance27",
              "rotation": "0",
              "type": "uiElement",
              "x": 35
            },
            {
              "texture": "tile_bg_2",
              "y": 35,
              "scaleX": "1",
              "scaleY": "1",
              "width": "40",
              "height": "40",
              "name": "instance29",
              "rotation": "0",
              "type": "uiElement",
              "x": 70
            },
            {
              "texture": "tile_bg_2",
              "y": 35,
              "scaleX": "1",
              "scaleY": "1",
              "width": "40",
              "height": "40",
              "name": "instance31",
              "rotation": "0",
              "type": "uiElement",
              "x": 105
            },
            {
              "texture": "tile_bg_2",
              "y": 35,
              "scaleX": "1",
              "scaleY": "1",
              "width": "40",
              "height": "40",
              "name": "instance33",
              "rotation": "0",
              "type": "uiElement",
              "x": 140
            },
            {
              "texture": "tile_bg_2",
              "y": 35,
              "scaleX": "1",
              "scaleY": "1",
              "width": "40",
              "height": "40",
              "name": "instance35",
              "rotation": "0",
              "type": "uiElement",
              "x": 175
            },
            {
              "texture": "tile_bg_2",
              "y": 35,
              "scaleX": "1",
              "scaleY": "1",
              "width": "40",
              "height": "40",
              "name": "instance37",
              "rotation": "0",
              "type": "uiElement",
              "x": 210
            },
            {
              "texture": "tile_bg_2",
              "y": 35,
              "scaleX": "1",
              "scaleY": "1",
              "width": "40",
              "height": "40",
              "name": "instance39",
              "rotation": "0",
              "type": "uiElement",
              "x": 245
            },
            {
              "texture": "tile_bg_2",
              "y": 35,
              "scaleX": "1",
              "scaleY": "1",
              "width": "40",
              "height": "40",
              "name": "instance41",
              "rotation": "0",
              "type": "uiElement",
              "x": 280
            },
            {
              "texture": "tile_bg_2",
              "y": 35,
              "scaleX": "1",
              "scaleY": "1",
              "width": "40",
              "height": "40",
              "name": "instance43",
              "rotation": "0",
              "type": "uiElement",
              "x": 315
            },
            {
              "texture": "tile_bg_2",
              "y": 35,
              "scaleX": "1",
              "scaleY": "1",
              "width": "40",
              "height": "40",
              "name": "instance45",
              "rotation": "0",
              "type": "uiElement",
              "x": 350
            },
            {
              "texture": "tile_bg_2",
              "y": 35,
              "scaleX": "1",
              "scaleY": "1",
              "width": "40",
              "height": "40",
              "name": "instance47",
              "rotation": "0",
              "type": "uiElement",
              "x": 385
            },
            {
              "texture": "tile_bg_2",
              "y": 35,
              "scaleX": "1",
              "scaleY": "1",
              "width": "40",
              "height": "40",
              "name": "instance49",
              "rotation": "0",
              "type": "uiElement",
              "x": 420
            },
            {
              "texture": "tile_bg_2",
              "y": 70,
              "scaleX": "1",
              "scaleY": "1",
              "width": "40",
              "height": "40",
              "name": "instance51",
              "rotation": "0",
              "type": "uiElement",
              "x": 35
            },
            {
              "texture": "tile_bg_2",
              "y": 70,
              "scaleX": "1",
              "scaleY": "1",
              "width": "40",
              "height": "40",
              "name": "instance53",
              "rotation": "0",
              "type": "uiElement",
              "x": 70
            },
            {
              "texture": "tile_bg_2",
              "y": 70,
              "scaleX": "1",
              "scaleY": "1",
              "width": "40",
              "height": "40",
              "name": "instance55",
              "rotation": "0",
              "type": "uiElement",
              "x": 105
            },
            {
              "texture": "tile_bg_2",
              "y": 70,
              "scaleX": "1",
              "scaleY": "1",
              "width": "40",
              "height": "40",
              "name": "instance57",
              "rotation": "0",
              "type": "uiElement",
              "x": 140
            },
            {
              "texture": "tile_bg_2",
              "y": 70,
              "scaleX": "1",
              "scaleY": "1",
              "width": "40",
              "height": "40",
              "name": "instance59",
              "rotation": "0",
              "type": "uiElement",
              "x": 175
            },
            {
              "texture": "tile_bg_2",
              "y": 70,
              "scaleX": "1",
              "scaleY": "1",
              "width": "40",
              "height": "40",
              "name": "instance61",
              "rotation": "0",
              "type": "uiElement",
              "x": 210
            },
            {
              "texture": "tile_bg_2",
              "y": 70,
              "scaleX": "1",
              "scaleY": "1",
              "width": "40",
              "height": "40",
              "name": "instance63",
              "rotation": "0",
              "type": "uiElement",
              "x": 245
            },
            {
              "texture": "tile_bg_2",
              "y": 70,
              "scaleX": "1",
              "scaleY": "1",
              "width": "40",
              "height": "40",
              "name": "instance65",
              "rotation": "0",
              "type": "uiElement",
              "x": 280
            },
            {
              "texture": "tile_bg_2",
              "y": 70,
              "scaleX": "1",
              "scaleY": "1",
              "width": "40",
              "height": "40",
              "name": "instance67",
              "rotation": "0",
              "type": "uiElement",
              "x": 315
            },
            {
              "texture": "tile_bg_2",
              "y": 70,
              "scaleX": "1",
              "scaleY": "1",
              "width": "40",
              "height": "40",
              "name": "instance69",
              "rotation": "0",
              "type": "uiElement",
              "x": 350
            },
            {
              "texture": "tile_bg_2",
              "y": 70,
              "scaleX": "1",
              "scaleY": "1",
              "width": "40",
              "height": "40",
              "name": "instance71",
              "rotation": "0",
              "type": "uiElement",
              "x": 385
            },
            {
              "texture": "tile_bg_2",
              "y": 70,
              "scaleX": "1",
              "scaleY": "1",
              "width": "40",
              "height": "40",
              "name": "instance73",
              "rotation": "0",
              "type": "uiElement",
              "x": 420
            },
            {
              "texture": "tile_bg_2",
              "y": 105,
              "scaleX": "1",
              "scaleY": "1",
              "width": "40",
              "height": "40",
              "name": "instance75",
              "rotation": "0",
              "type": "uiElement",
              "x": 35
            },
            {
              "texture": "tile_bg_2",
              "y": 105,
              "scaleX": "1",
              "scaleY": "1",
              "width": "40",
              "height": "40",
              "name": "instance77",
              "rotation": "0",
              "type": "uiElement",
              "x": 70
            },
            {
              "texture": "tile_bg_2",
              "y": 105,
              "scaleX": "1",
              "scaleY": "1",
              "width": "40",
              "height": "40",
              "name": "instance79",
              "rotation": "0",
              "type": "uiElement",
              "x": 105
            },
            {
              "texture": "tile_bg_2",
              "y": 105,
              "scaleX": "1",
              "scaleY": "1",
              "width": "40",
              "height": "40",
              "name": "instance81",
              "rotation": "0",
              "type": "uiElement",
              "x": 140
            },
            {
              "texture": "tile_bg_2",
              "y": 105,
              "scaleX": "1",
              "scaleY": "1",
              "width": "40",
              "height": "40",
              "name": "instance83",
              "rotation": "0",
              "type": "uiElement",
              "x": 175
            },
            {
              "texture": "tile_bg_2",
              "y": 105,
              "scaleX": "1",
              "scaleY": "1",
              "width": "40",
              "height": "40",
              "name": "instance85",
              "rotation": "0",
              "type": "uiElement",
              "x": 210
            },
            {
              "texture": "tile_bg_2",
              "y": 105,
              "scaleX": "1",
              "scaleY": "1",
              "width": "40",
              "height": "40",
              "name": "instance87",
              "rotation": "0",
              "type": "uiElement",
              "x": 245
            },
            {
              "texture": "tile_bg_2",
              "y": 105,
              "scaleX": "1",
              "scaleY": "1",
              "width": "40",
              "height": "40",
              "name": "instance89",
              "rotation": "0",
              "type": "uiElement",
              "x": 280
            },
            {
              "texture": "tile_bg_2",
              "y": 105,
              "scaleX": "1",
              "scaleY": "1",
              "width": "40",
              "height": "40",
              "name": "instance91",
              "rotation": "0",
              "type": "uiElement",
              "x": 315
            },
            {
              "texture": "tile_bg_2",
              "y": 105,
              "scaleX": "1",
              "scaleY": "1",
              "width": "40",
              "height": "40",
              "name": "instance93",
              "rotation": "0",
              "type": "uiElement",
              "x": 350
            },
            {
              "texture": "tile_bg_2",
              "y": 105,
              "scaleX": "1",
              "scaleY": "1",
              "width": "40",
              "height": "40",
              "name": "instance95",
              "rotation": "0",
              "type": "uiElement",
              "x": 385
            },
            {
              "texture": "tile_bg_2",
              "y": 105,
              "scaleX": "1",
              "scaleY": "1",
              "width": "40",
              "height": "40",
              "name": "instance97",
              "rotation": "0",
              "type": "uiElement",
              "x": 420
            },
            {
              "texture": "tile_bg_1",
              "y": 140,
              "scaleX": "1",
              "scaleY": "1",
              "width": "40",
              "height": "40",
              "name": "instance99",
              "rotation": "0",
              "type": "uiElement",
              "x": 0
            },
            {
              "texture": "tile_bg_2",
              "y": 0,
              "scaleX": "1",
              "scaleY": "1",
              "width": "40",
              "height": "40",
              "name": "instance101",
              "rotation": "0",
              "type": "uiElement",
              "x": 35
            },
            {
              "texture": "tile_bg_2",
              "y": 0,
              "scaleX": "1",
              "scaleY": "1",
              "width": "40",
              "height": "40",
              "name": "instance103",
              "rotation": "0",
              "type": "uiElement",
              "x": 70
            },
            {
              "texture": "tile_bg_2",
              "y": 0,
              "scaleX": "1",
              "scaleY": "1",
              "width": "40",
              "height": "40",
              "name": "instance105",
              "rotation": "0",
              "type": "uiElement",
              "x": 105
            },
            {
              "texture": "tile_bg_2",
              "y": 0,
              "scaleX": "1",
              "scaleY": "1",
              "width": "40",
              "height": "40",
              "name": "instance107",
              "rotation": "0",
              "type": "uiElement",
              "x": 140
            },
            {
              "texture": "tile_bg_2",
              "y": 0,
              "scaleX": "1",
              "scaleY": "1",
              "width": "40",
              "height": "40",
              "name": "instance109",
              "rotation": "0",
              "type": "uiElement",
              "x": 175
            },
            {
              "texture": "tile_bg_2",
              "y": 0,
              "scaleX": "1",
              "scaleY": "1",
              "width": "40",
              "height": "40",
              "name": "instance111",
              "rotation": "0",
              "type": "uiElement",
              "x": 210
            },
            {
              "texture": "tile_bg_2",
              "y": 0,
              "scaleX": "1",
              "scaleY": "1",
              "width": "40",
              "height": "40",
              "name": "instance113",
              "rotation": "0",
              "type": "uiElement",
              "x": 245
            },
            {
              "texture": "tile_bg_2",
              "y": 0,
              "scaleX": "1",
              "scaleY": "1",
              "width": "40",
              "height": "40",
              "name": "instance115",
              "rotation": "0",
              "type": "uiElement",
              "x": 280
            },
            {
              "texture": "tile_bg_2",
              "y": 0,
              "scaleX": "1",
              "scaleY": "1",
              "width": "40",
              "height": "40",
              "name": "instance117",
              "rotation": "0",
              "type": "uiElement",
              "x": 315
            },
            {
              "texture": "tile_bg_2",
              "y": 0,
              "scaleX": "1",
              "scaleY": "1",
              "width": "40",
              "height": "40",
              "name": "instance119",
              "rotation": "0",
              "type": "uiElement",
              "x": 350
            },
            {
              "texture": "tile_bg_1",
              "y": 140,
              "scaleX": "1",
              "scaleY": "1",
              "width": "-40",
              "height": "40",
              "name": "instance121",
              "rotation": "0",
              "type": "uiElement",
              "x": 495
            },
            {
              "texture": "tile_bg_2",
              "y": 35,
              "scaleX": "1.00",
              "scaleY": "1.00",
              "width": "-40",
              "height": "40",
              "name": "instance123",
              "rotation": "-1.57",
              "type": "uiElement",
              "x": 0
            },
            {
              "texture": "tile_bg_1",
              "y": 40,
              "scaleX": "1",
              "scaleY": "1",
              "width": "40",
              "height": "-40",
              "name": "instance125",
              "rotation": "0",
              "type": "uiElement",
              "x": 0
            },
            {
              "texture": "tile_bg_1",
              "y": 40,
              "scaleX": "1",
              "scaleY": "1",
              "width": "-40",
              "height": "-40",
              "name": "instance127",
              "rotation": "0",
              "type": "uiElement",
              "x": 495
            },
            {
              "texture": "tile_bg_2",
              "y": 35,
              "scaleX": "1.00",
              "scaleY": "1.00",
              "width": "40",
              "height": "40",
              "name": "instance129",
              "rotation": "1.57",
              "type": "uiElement",
              "x": 495
            },
            {
              "texture": "tile_bg_2",
              "y": 70,
              "scaleX": "1.00",
              "scaleY": "1.00",
              "width": "-40",
              "height": "40",
              "name": "instance131",
              "rotation": "-1.57",
              "type": "uiElement",
              "x": 0
            },
            {
              "texture": "tile_bg_2",
              "y": 105,
              "scaleX": "1.00",
              "scaleY": "1.00",
              "width": "-40",
              "height": "40",
              "name": "instance133",
              "rotation": "-1.57",
              "type": "uiElement",
              "x": 0
            },
            {
              "texture": "tile_bg_2",
              "y": 0,
              "scaleX": "1",
              "scaleY": "1",
              "width": "40",
              "height": "40",
              "name": "instance135",
              "rotation": "0",
              "type": "uiElement",
              "x": 385
            },
            {
              "texture": "tile_bg_2",
              "y": 0,
              "scaleX": "1",
              "scaleY": "1",
              "width": "40",
              "height": "40",
              "name": "instance137",
              "rotation": "0",
              "type": "uiElement",
              "x": 420
            },
            {
              "texture": "tile_bg_2",
              "y": 70,
              "scaleX": "1.00",
              "scaleY": "1.00",
              "width": "40",
              "height": "40",
              "name": "instance139",
              "rotation": "1.57",
              "type": "uiElement",
              "x": 495
            },
            {
              "texture": "tile_bg_2",
              "y": 105,
              "scaleX": "1.00",
              "scaleY": "1.00",
              "width": "40",
              "height": "40",
              "name": "instance141",
              "rotation": "1.57",
              "type": "uiElement",
              "x": 495
            },
            {
              "texture": "tile_bg_2",
              "y": 140,
              "scaleX": "1",
              "scaleY": "1",
              "width": "40",
              "height": "40",
              "name": "instance143",
              "rotation": "0",
              "type": "uiElement",
              "x": 35
            },
            {
              "texture": "tile_bg_2",
              "y": 140,
              "scaleX": "1",
              "scaleY": "1",
              "width": "40",
              "height": "40",
              "name": "instance145",
              "rotation": "0",
              "type": "uiElement",
              "x": 70
            },
            {
              "texture": "tile_bg_2",
              "y": 140,
              "scaleX": "1",
              "scaleY": "1",
              "width": "40",
              "height": "40",
              "name": "instance147",
              "rotation": "0",
              "type": "uiElement",
              "x": 105
            },
            {
              "texture": "tile_bg_2",
              "y": 140,
              "scaleX": "1",
              "scaleY": "1",
              "width": "40",
              "height": "40",
              "name": "instance149",
              "rotation": "0",
              "type": "uiElement",
              "x": 140
            },
            {
              "texture": "tile_bg_2",
              "y": 140,
              "scaleX": "1",
              "scaleY": "1",
              "width": "40",
              "height": "40",
              "name": "instance151",
              "rotation": "0",
              "type": "uiElement",
              "x": 175
            },
            {
              "texture": "tile_bg_2",
              "y": 140,
              "scaleX": "1",
              "scaleY": "1",
              "width": "40",
              "height": "40",
              "name": "instance153",
              "rotation": "0",
              "type": "uiElement",
              "x": 210
            },
            {
              "texture": "tile_bg_2",
              "y": 140,
              "scaleX": "1",
              "scaleY": "1",
              "width": "40",
              "height": "40",
              "name": "instance155",
              "rotation": "0",
              "type": "uiElement",
              "x": 245
            },
            {
              "texture": "tile_bg_2",
              "y": 140,
              "scaleX": "1",
              "scaleY": "1",
              "width": "40",
              "height": "40",
              "name": "instance157",
              "rotation": "0",
              "type": "uiElement",
              "x": 280
            },
            {
              "texture": "tile_bg_2",
              "y": 140,
              "scaleX": "1",
              "scaleY": "1",
              "width": "40",
              "height": "40",
              "name": "instance159",
              "rotation": "0",
              "type": "uiElement",
              "x": 315
            },
            {
              "texture": "tile_bg_2",
              "y": 140,
              "scaleX": "1",
              "scaleY": "1",
              "width": "40",
              "height": "40",
              "name": "instance161",
              "rotation": "0",
              "type": "uiElement",
              "x": 350
            },
            {
              "texture": "tile_bg_2",
              "y": 140,
              "scaleX": "1",
              "scaleY": "1",
              "width": "40",
              "height": "40",
              "name": "instance163",
              "rotation": "0",
              "type": "uiElement",
              "x": 385
            },
            {
              "texture": "tile_bg_2",
              "y": 140,
              "scaleX": "1",
              "scaleY": "1",
              "width": "40",
              "height": "40",
              "name": "instance165",
              "rotation": "0",
              "type": "uiElement",
              "x": 420
            }
          ],
          "type": "uiElement",
          "x": -247
        },
        {
          "rotation": "0",
          "hoverSprite": "button_2_rollover",
          "width": "140",
          "height": "48",
          "name": "no",
          "downSprite": "button_2_rollover",
          "x": 75,
          "y": 26,
          "scaleY": "1",
          "scaleX": "1",
          "upSprite": "button_2",
          "type": "uiButton"
        },
        {
          "rotation": "0",
          "hoverSprite": "button_2_rollover",
          "width": "140",
          "height": "48",
          "name": "yes",
          "downSprite": "button_2_rollover",
          "x": -213,
          "y": 26,
          "scaleY": "1",
          "scaleX": "1",
          "upSprite": "button_2",
          "type": "uiButton"
        },
        {
          "rotation": "0",
          "hoverSprite": "button_2_rollover",
          "width": "140",
          "height": "48",
          "name": "ok",
          "downSprite": "button_2_rollover",
          "x": -69,
          "y": 26,
          "scaleY": "1",
          "scaleX": "1",
          "upSprite": "button_2",
          "type": "uiButton"
        }
      ]
    },
    {
      "layoutName": "portrait",
      "children": [
        {
          "rotation": "0",
          "y": -90,
          "scaleX": "1",
          "scaleY": "1",
          "width": "546.70",
          "height": "202.65",
          "name": "back",
          "children": [
            {
              "texture": "shadow",
              "y": -10,
              "scaleX": "11.88",
              "scaleY": "4.40",
              "width": "546.70",
              "height": "202.65",
              "name": "instance189",
              "rotation": "0",
              "type": "uiElement",
              "x": -26
            },
            {
              "texture": "tile_bg_2",
              "y": 35,
              "scaleX": "1",
              "scaleY": "1",
              "width": "40",
              "height": "40",
              "name": "instance191",
              "rotation": "0",
              "type": "uiElement",
              "x": 35
            },
            {
              "texture": "tile_bg_2",
              "y": 35,
              "scaleX": "1",
              "scaleY": "1",
              "width": "40",
              "height": "40",
              "name": "instance193",
              "rotation": "0",
              "type": "uiElement",
              "x": 70
            },
            {
              "texture": "tile_bg_2",
              "y": 35,
              "scaleX": "1",
              "scaleY": "1",
              "width": "40",
              "height": "40",
              "name": "instance195",
              "rotation": "0",
              "type": "uiElement",
              "x": 105
            },
            {
              "texture": "tile_bg_2",
              "y": 35,
              "scaleX": "1",
              "scaleY": "1",
              "width": "40",
              "height": "40",
              "name": "instance197",
              "rotation": "0",
              "type": "uiElement",
              "x": 140
            },
            {
              "texture": "tile_bg_2",
              "y": 35,
              "scaleX": "1",
              "scaleY": "1",
              "width": "40",
              "height": "40",
              "name": "instance199",
              "rotation": "0",
              "type": "uiElement",
              "x": 175
            },
            {
              "texture": "tile_bg_2",
              "y": 35,
              "scaleX": "1",
              "scaleY": "1",
              "width": "40",
              "height": "40",
              "name": "instance201",
              "rotation": "0",
              "type": "uiElement",
              "x": 210
            },
            {
              "texture": "tile_bg_2",
              "y": 35,
              "scaleX": "1",
              "scaleY": "1",
              "width": "40",
              "height": "40",
              "name": "instance203",
              "rotation": "0",
              "type": "uiElement",
              "x": 245
            },
            {
              "texture": "tile_bg_2",
              "y": 35,
              "scaleX": "1",
              "scaleY": "1",
              "width": "40",
              "height": "40",
              "name": "instance205",
              "rotation": "0",
              "type": "uiElement",
              "x": 280
            },
            {
              "texture": "tile_bg_2",
              "y": 35,
              "scaleX": "1",
              "scaleY": "1",
              "width": "40",
              "height": "40",
              "name": "instance207",
              "rotation": "0",
              "type": "uiElement",
              "x": 315
            },
            {
              "texture": "tile_bg_2",
              "y": 35,
              "scaleX": "1",
              "scaleY": "1",
              "width": "40",
              "height": "40",
              "name": "instance209",
              "rotation": "0",
              "type": "uiElement",
              "x": 350
            },
            {
              "texture": "tile_bg_2",
              "y": 35,
              "scaleX": "1",
              "scaleY": "1",
              "width": "40",
              "height": "40",
              "name": "instance211",
              "rotation": "0",
              "type": "uiElement",
              "x": 385
            },
            {
              "texture": "tile_bg_2",
              "y": 35,
              "scaleX": "1",
              "scaleY": "1",
              "width": "40",
              "height": "40",
              "name": "instance213",
              "rotation": "0",
              "type": "uiElement",
              "x": 420
            },
            {
              "texture": "tile_bg_2",
              "y": 70,
              "scaleX": "1",
              "scaleY": "1",
              "width": "40",
              "height": "40",
              "name": "instance215",
              "rotation": "0",
              "type": "uiElement",
              "x": 35
            },
            {
              "texture": "tile_bg_2",
              "y": 70,
              "scaleX": "1",
              "scaleY": "1",
              "width": "40",
              "height": "40",
              "name": "instance217",
              "rotation": "0",
              "type": "uiElement",
              "x": 70
            },
            {
              "texture": "tile_bg_2",
              "y": 70,
              "scaleX": "1",
              "scaleY": "1",
              "width": "40",
              "height": "40",
              "name": "instance219",
              "rotation": "0",
              "type": "uiElement",
              "x": 105
            },
            {
              "texture": "tile_bg_2",
              "y": 70,
              "scaleX": "1",
              "scaleY": "1",
              "width": "40",
              "height": "40",
              "name": "instance221",
              "rotation": "0",
              "type": "uiElement",
              "x": 140
            },
            {
              "texture": "tile_bg_2",
              "y": 70,
              "scaleX": "1",
              "scaleY": "1",
              "width": "40",
              "height": "40",
              "name": "instance223",
              "rotation": "0",
              "type": "uiElement",
              "x": 175
            },
            {
              "texture": "tile_bg_2",
              "y": 70,
              "scaleX": "1",
              "scaleY": "1",
              "width": "40",
              "height": "40",
              "name": "instance225",
              "rotation": "0",
              "type": "uiElement",
              "x": 210
            },
            {
              "texture": "tile_bg_2",
              "y": 70,
              "scaleX": "1",
              "scaleY": "1",
              "width": "40",
              "height": "40",
              "name": "instance227",
              "rotation": "0",
              "type": "uiElement",
              "x": 245
            },
            {
              "texture": "tile_bg_2",
              "y": 70,
              "scaleX": "1",
              "scaleY": "1",
              "width": "40",
              "height": "40",
              "name": "instance229",
              "rotation": "0",
              "type": "uiElement",
              "x": 280
            },
            {
              "texture": "tile_bg_2",
              "y": 70,
              "scaleX": "1",
              "scaleY": "1",
              "width": "40",
              "height": "40",
              "name": "instance231",
              "rotation": "0",
              "type": "uiElement",
              "x": 315
            },
            {
              "texture": "tile_bg_2",
              "y": 70,
              "scaleX": "1",
              "scaleY": "1",
              "width": "40",
              "height": "40",
              "name": "instance233",
              "rotation": "0",
              "type": "uiElement",
              "x": 350
            },
            {
              "texture": "tile_bg_2",
              "y": 70,
              "scaleX": "1",
              "scaleY": "1",
              "width": "40",
              "height": "40",
              "name": "instance235",
              "rotation": "0",
              "type": "uiElement",
              "x": 385
            },
            {
              "texture": "tile_bg_2",
              "y": 70,
              "scaleX": "1",
              "scaleY": "1",
              "width": "40",
              "height": "40",
              "name": "instance237",
              "rotation": "0",
              "type": "uiElement",
              "x": 420
            },
            {
              "texture": "tile_bg_2",
              "y": 105,
              "scaleX": "1",
              "scaleY": "1",
              "width": "40",
              "height": "40",
              "name": "instance239",
              "rotation": "0",
              "type": "uiElement",
              "x": 35
            },
            {
              "texture": "tile_bg_2",
              "y": 105,
              "scaleX": "1",
              "scaleY": "1",
              "width": "40",
              "height": "40",
              "name": "instance241",
              "rotation": "0",
              "type": "uiElement",
              "x": 70
            },
            {
              "texture": "tile_bg_2",
              "y": 105,
              "scaleX": "1",
              "scaleY": "1",
              "width": "40",
              "height": "40",
              "name": "instance243",
              "rotation": "0",
              "type": "uiElement",
              "x": 105
            },
            {
              "texture": "tile_bg_2",
              "y": 105,
              "scaleX": "1",
              "scaleY": "1",
              "width": "40",
              "height": "40",
              "name": "instance245",
              "rotation": "0",
              "type": "uiElement",
              "x": 140
            },
            {
              "texture": "tile_bg_2",
              "y": 105,
              "scaleX": "1",
              "scaleY": "1",
              "width": "40",
              "height": "40",
              "name": "instance247",
              "rotation": "0",
              "type": "uiElement",
              "x": 175
            },
            {
              "texture": "tile_bg_2",
              "y": 105,
              "scaleX": "1",
              "scaleY": "1",
              "width": "40",
              "height": "40",
              "name": "instance249",
              "rotation": "0",
              "type": "uiElement",
              "x": 210
            },
            {
              "texture": "tile_bg_2",
              "y": 105,
              "scaleX": "1",
              "scaleY": "1",
              "width": "40",
              "height": "40",
              "name": "instance251",
              "rotation": "0",
              "type": "uiElement",
              "x": 245
            },
            {
              "texture": "tile_bg_2",
              "y": 105,
              "scaleX": "1",
              "scaleY": "1",
              "width": "40",
              "height": "40",
              "name": "instance253",
              "rotation": "0",
              "type": "uiElement",
              "x": 280
            },
            {
              "texture": "tile_bg_2",
              "y": 105,
              "scaleX": "1",
              "scaleY": "1",
              "width": "40",
              "height": "40",
              "name": "instance255",
              "rotation": "0",
              "type": "uiElement",
              "x": 315
            },
            {
              "texture": "tile_bg_2",
              "y": 105,
              "scaleX": "1",
              "scaleY": "1",
              "width": "40",
              "height": "40",
              "name": "instance257",
              "rotation": "0",
              "type": "uiElement",
              "x": 350
            },
            {
              "texture": "tile_bg_2",
              "y": 105,
              "scaleX": "1",
              "scaleY": "1",
              "width": "40",
              "height": "40",
              "name": "instance259",
              "rotation": "0",
              "type": "uiElement",
              "x": 385
            },
            {
              "texture": "tile_bg_2",
              "y": 105,
              "scaleX": "1",
              "scaleY": "1",
              "width": "40",
              "height": "40",
              "name": "instance261",
              "rotation": "0",
              "type": "uiElement",
              "x": 420
            },
            {
              "texture": "tile_bg_1",
              "y": 140,
              "scaleX": "1",
              "scaleY": "1",
              "width": "40",
              "height": "40",
              "name": "instance263",
              "rotation": "0",
              "type": "uiElement",
              "x": 0
            },
            {
              "texture": "tile_bg_2",
              "y": 0,
              "scaleX": "1",
              "scaleY": "1",
              "width": "40",
              "height": "40",
              "name": "instance265",
              "rotation": "0",
              "type": "uiElement",
              "x": 35
            },
            {
              "texture": "tile_bg_2",
              "y": 0,
              "scaleX": "1",
              "scaleY": "1",
              "width": "40",
              "height": "40",
              "name": "instance267",
              "rotation": "0",
              "type": "uiElement",
              "x": 70
            },
            {
              "texture": "tile_bg_2",
              "y": 0,
              "scaleX": "1",
              "scaleY": "1",
              "width": "40",
              "height": "40",
              "name": "instance269",
              "rotation": "0",
              "type": "uiElement",
              "x": 105
            },
            {
              "texture": "tile_bg_2",
              "y": 0,
              "scaleX": "1",
              "scaleY": "1",
              "width": "40",
              "height": "40",
              "name": "instance271",
              "rotation": "0",
              "type": "uiElement",
              "x": 140
            },
            {
              "texture": "tile_bg_2",
              "y": 0,
              "scaleX": "1",
              "scaleY": "1",
              "width": "40",
              "height": "40",
              "name": "instance273",
              "rotation": "0",
              "type": "uiElement",
              "x": 175
            },
            {
              "texture": "tile_bg_2",
              "y": 0,
              "scaleX": "1",
              "scaleY": "1",
              "width": "40",
              "height": "40",
              "name": "instance275",
              "rotation": "0",
              "type": "uiElement",
              "x": 210
            },
            {
              "texture": "tile_bg_2",
              "y": 0,
              "scaleX": "1",
              "scaleY": "1",
              "width": "40",
              "height": "40",
              "name": "instance277",
              "rotation": "0",
              "type": "uiElement",
              "x": 245
            },
            {
              "texture": "tile_bg_2",
              "y": 0,
              "scaleX": "1",
              "scaleY": "1",
              "width": "40",
              "height": "40",
              "name": "instance279",
              "rotation": "0",
              "type": "uiElement",
              "x": 280
            },
            {
              "texture": "tile_bg_2",
              "y": 0,
              "scaleX": "1",
              "scaleY": "1",
              "width": "40",
              "height": "40",
              "name": "instance281",
              "rotation": "0",
              "type": "uiElement",
              "x": 315
            },
            {
              "texture": "tile_bg_2",
              "y": 0,
              "scaleX": "1",
              "scaleY": "1",
              "width": "40",
              "height": "40",
              "name": "instance283",
              "rotation": "0",
              "type": "uiElement",
              "x": 350
            },
            {
              "texture": "tile_bg_1",
              "y": 140,
              "scaleX": "1",
              "scaleY": "1",
              "width": "-40",
              "height": "40",
              "name": "instance285",
              "rotation": "0",
              "type": "uiElement",
              "x": 495
            },
            {
              "texture": "tile_bg_2",
              "y": 35,
              "scaleX": "1.00",
              "scaleY": "1.00",
              "width": "-40",
              "height": "40",
              "name": "instance287",
              "rotation": "-1.57",
              "type": "uiElement",
              "x": 0
            },
            {
              "texture": "tile_bg_1",
              "y": 40,
              "scaleX": "1",
              "scaleY": "1",
              "width": "40",
              "height": "-40",
              "name": "instance289",
              "rotation": "0",
              "type": "uiElement",
              "x": 0
            },
            {
              "texture": "tile_bg_1",
              "y": 40,
              "scaleX": "1",
              "scaleY": "1",
              "width": "-40",
              "height": "-40",
              "name": "instance291",
              "rotation": "0",
              "type": "uiElement",
              "x": 495
            },
            {
              "texture": "tile_bg_2",
              "y": 35,
              "scaleX": "1.00",
              "scaleY": "1.00",
              "width": "40",
              "height": "40",
              "name": "instance293",
              "rotation": "1.57",
              "type": "uiElement",
              "x": 495
            },
            {
              "texture": "tile_bg_2",
              "y": 70,
              "scaleX": "1.00",
              "scaleY": "1.00",
              "width": "-40",
              "height": "40",
              "name": "instance295",
              "rotation": "-1.57",
              "type": "uiElement",
              "x": 0
            },
            {
              "texture": "tile_bg_2",
              "y": 105,
              "scaleX": "1.00",
              "scaleY": "1.00",
              "width": "-40",
              "height": "40",
              "name": "instance297",
              "rotation": "-1.57",
              "type": "uiElement",
              "x": 0
            },
            {
              "texture": "tile_bg_2",
              "y": 0,
              "scaleX": "1",
              "scaleY": "1",
              "width": "40",
              "height": "40",
              "name": "instance299",
              "rotation": "0",
              "type": "uiElement",
              "x": 385
            },
            {
              "texture": "tile_bg_2",
              "y": 0,
              "scaleX": "1",
              "scaleY": "1",
              "width": "40",
              "height": "40",
              "name": "instance301",
              "rotation": "0",
              "type": "uiElement",
              "x": 420
            },
            {
              "texture": "tile_bg_2",
              "y": 70,
              "scaleX": "1.00",
              "scaleY": "1.00",
              "width": "40",
              "height": "40",
              "name": "instance303",
              "rotation": "1.57",
              "type": "uiElement",
              "x": 495
            },
            {
              "texture": "tile_bg_2",
              "y": 105,
              "scaleX": "1.00",
              "scaleY": "1.00",
              "width": "40",
              "height": "40",
              "name": "instance305",
              "rotation": "1.57",
              "type": "uiElement",
              "x": 495
            },
            {
              "texture": "tile_bg_2",
              "y": 140,
              "scaleX": "1",
              "scaleY": "1",
              "width": "40",
              "height": "40",
              "name": "instance307",
              "rotation": "0",
              "type": "uiElement",
              "x": 35
            },
            {
              "texture": "tile_bg_2",
              "y": 140,
              "scaleX": "1",
              "scaleY": "1",
              "width": "40",
              "height": "40",
              "name": "instance309",
              "rotation": "0",
              "type": "uiElement",
              "x": 70
            },
            {
              "texture": "tile_bg_2",
              "y": 140,
              "scaleX": "1",
              "scaleY": "1",
              "width": "40",
              "height": "40",
              "name": "instance311",
              "rotation": "0",
              "type": "uiElement",
              "x": 105
            },
            {
              "texture": "tile_bg_2",
              "y": 140,
              "scaleX": "1",
              "scaleY": "1",
              "width": "40",
              "height": "40",
              "name": "instance313",
              "rotation": "0",
              "type": "uiElement",
              "x": 140
            },
            {
              "texture": "tile_bg_2",
              "y": 140,
              "scaleX": "1",
              "scaleY": "1",
              "width": "40",
              "height": "40",
              "name": "instance315",
              "rotation": "0",
              "type": "uiElement",
              "x": 175
            },
            {
              "texture": "tile_bg_2",
              "y": 140,
              "scaleX": "1",
              "scaleY": "1",
              "width": "40",
              "height": "40",
              "name": "instance317",
              "rotation": "0",
              "type": "uiElement",
              "x": 210
            },
            {
              "texture": "tile_bg_2",
              "y": 140,
              "scaleX": "1",
              "scaleY": "1",
              "width": "40",
              "height": "40",
              "name": "instance319",
              "rotation": "0",
              "type": "uiElement",
              "x": 245
            },
            {
              "texture": "tile_bg_2",
              "y": 140,
              "scaleX": "1",
              "scaleY": "1",
              "width": "40",
              "height": "40",
              "name": "instance321",
              "rotation": "0",
              "type": "uiElement",
              "x": 280
            },
            {
              "texture": "tile_bg_2",
              "y": 140,
              "scaleX": "1",
              "scaleY": "1",
              "width": "40",
              "height": "40",
              "name": "instance323",
              "rotation": "0",
              "type": "uiElement",
              "x": 315
            },
            {
              "texture": "tile_bg_2",
              "y": 140,
              "scaleX": "1",
              "scaleY": "1",
              "width": "40",
              "height": "40",
              "name": "instance325",
              "rotation": "0",
              "type": "uiElement",
              "x": 350
            },
            {
              "texture": "tile_bg_2",
              "y": 140,
              "scaleX": "1",
              "scaleY": "1",
              "width": "40",
              "height": "40",
              "name": "instance327",
              "rotation": "0",
              "type": "uiElement",
              "x": 385
            },
            {
              "texture": "tile_bg_2",
              "y": 140,
              "scaleX": "1",
              "scaleY": "1",
              "width": "40",
              "height": "40",
              "name": "instance329",
              "rotation": "0",
              "type": "uiElement",
              "x": 420
            }
          ],
          "type": "uiElement",
          "x": -247
        },
        {
          "rotation": "0",
          "hoverSprite": "button_2_rollover",
          "width": "140",
          "height": "48",
          "name": "no",
          "downSprite": "button_2_rollover",
          "x": 75,
          "y": 26,
          "scaleY": "1",
          "scaleX": "1",
          "upSprite": "button_2",
          "type": "uiButton"
        },
        {
          "rotation": "0",
          "hoverSprite": "button_2_rollover",
          "width": "140",
          "height": "48",
          "name": "yes",
          "downSprite": "button_2_rollover",
          "x": -213,
          "y": 26,
          "scaleY": "1",
          "scaleX": "1",
          "upSprite": "button_2",
          "type": "uiButton"
        },
        {
          "rotation": "0",
          "hoverSprite": "button_2_rollover",
          "width": "140",
          "height": "48",
          "name": "ok",
          "downSprite": "button_2_rollover",
          "x": -69,
          "y": 26,
          "scaleY": "1",
          "scaleX": "1",
          "upSprite": "button_2",
          "type": "uiButton"
        }
      ]
    }
  ]
}
